laeplooth/__init__.py
laeplooth/__main__.py
laeplooth/main.py
laeplooth/test.py
laeplooth/testall.py
laeplooth-0.6.2.dist-info/METADATA
laeplooth-0.6.2.dist-info/WHEEL
laeplooth-0.6.2.dist-info/entry_points.txt
laeplooth-0.6.2.dist-info/top_level.txt
laeplooth-0.6.2.dist-info/RECORD
