Metadata-Version: 2.1
Name: laeplooth
Version: 0.6.2
Summary: Translator for loo language
Author: most.warong
Requires-Dist: pythainlp ==2.1.4
